paymentwall/__init__.py
paymentwall/base.py
paymentwall/pingback.py
paymentwall/product.py
paymentwall/widget.py
paymentwall_python-1.0.9.dist-info/licenses/LICENSE
paymentwall_python-1.0.9.dist-info/METADATA
paymentwall_python-1.0.9.dist-info/WHEEL
paymentwall_python-1.0.9.dist-info/top_level.txt
paymentwall_python-1.0.9.dist-info/RECORD
