Metadata-Version: 2.4
Name: paymentwall-python
Version: 1.0.9
Summary: Paymentwall Python Library
Home-page: https://github.com/paymentwall/paymentwall-python
Author: Paymentwall Team
Author-email: devsupport@paymentwall.com
License: MIT
Requires-Python: >=3.6
License-File: LICENSE
Dynamic: author
Dynamic: author-email
Dynamic: description
Dynamic: home-page
Dynamic: license
Dynamic: license-file
Dynamic: requires-python
Dynamic: summary
